meo/__init__.py
meo/config/__init__.py
meo/config/default_settings.py
meo/evaluators/__init__.py
meo/evaluators/metrics.py
meo/evaluators/reward.py
meo/integrations/__init__.py
meo/integrations/autogen_wrapper.py
meo/integrations/langchain_wrapper.py
meo/memory/__init__.py
meo/memory/episodic.py
meo/memory/semantic.py
meo/memory/storage.py
meo/meta/__init__.py
meo/meta/policy_adapter.py
meo/orchestrator/__init__.py
meo/orchestrator/hooks.py
meo/orchestrator/wrappers.py
meo/utils/__init__.py
meo/utils/encoders.py
meo/utils/logging.py
synapse_meo-0.1.0.dist-info/licenses/LICENSE
synapse_meo-0.1.0.dist-info/METADATA
synapse_meo-0.1.0.dist-info/WHEEL
synapse_meo-0.1.0.dist-info/top_level.txt
synapse_meo-0.1.0.dist-info/RECORD
