Metadata-Version: 2.4
Name: synapse-meo
Version: 0.1.0
Summary: Memory Embedded Orchestration - A foundational layer for agentic AI systems with persistent memory, evaluation, and meta-policy adaptation
Author: Synapse Data / Ivan Lluch
License: Apache-2.0
Project-URL: Homepage, https://github.com/yourusername/meo
Project-URL: Documentation, https://github.com/yourusername/meo/blob/main/README.md
Project-URL: Repository, https://github.com/yourusername/meo
Keywords: ai,agents,orchestration,memory,reinforcement-learning,meta-learning
Classifier: Development Status :: 3 - Alpha
Classifier: Intended Audience :: Developers
Classifier: License :: OSI Approved :: Apache Software License
Classifier: Programming Language :: Python :: 3
Classifier: Programming Language :: Python :: 3.8
Classifier: Programming Language :: Python :: 3.9
Classifier: Programming Language :: Python :: 3.10
Classifier: Programming Language :: Python :: 3.11
Classifier: Topic :: Scientific/Engineering :: Artificial Intelligence
Requires-Python: >=3.8
License-File: LICENSE
Requires-Dist: numpy>=1.20.0
Requires-Dist: typing-extensions>=4.0.0
Provides-Extra: dev
Requires-Dist: pytest>=7.0.0; extra == "dev"
Requires-Dist: black>=22.0.0; extra == "dev"
Requires-Dist: mypy>=0.950; extra == "dev"
Provides-Extra: langchain
Requires-Dist: langchain>=0.1.0; extra == "langchain"
Provides-Extra: autogen
Requires-Dist: pyautogen>=0.2.0; extra == "autogen"
Dynamic: license-file
Dynamic: requires-python
